asynql/__init__.py
asynql/gqlfield.py
asynql/gqlmodel.py
asynql/gqlquery.py
asynql-0.1.0.dist-info/LICENSE
asynql-0.1.0.dist-info/WHEEL
asynql-0.1.0.dist-info/METADATA
asynql-0.1.0.dist-info/RECORD
